tripleodash/__init__.py
tripleodash/__main__.py
tripleodash/clients.py
tripleodash/dash.py
tripleodash/palette.py
tripleodash/util.py
tripleodash/sections/__init__.py
tripleodash/sections/about.py
tripleodash/sections/base.py
tripleodash/sections/images.py
tripleodash/sections/nodes.py
tripleodash/sections/overview.py
tripleodash/sections/servers.py
tripleodash/sections/stacks.py
tripleodash/tests/__init__.py
tripleodash/tests/base.py
tripleodash/tests/test_dash.py
tripleodash/tests/test_util.py
tripleodash/tests/sections/__init__.py
tripleodash/tests/sections/test_base.py
tripleodash/tests/sections/test_images.py
tripleodash/tests/sections/test_nodes.py
tripleodash/tests/sections/test_overview.py
tripleodash/tests/sections/test_servers.py
tripleodash/tests/sections/test_stacks.py
python_tripleodash-0.1.12.dist-info/entry_points.txt
python_tripleodash-0.1.12.dist-info/top_level.txt
python_tripleodash-0.1.12.dist-info/pbr.json
python_tripleodash-0.1.12.dist-info/METADATA
python_tripleodash-0.1.12.dist-info/DESCRIPTION.rst
python_tripleodash-0.1.12.dist-info/metadata.json
python_tripleodash-0.1.12.dist-info/WHEEL
python_tripleodash-0.1.12.dist-info/RECORD
