Metadata-Version: 2.0
Name: python-tripleodash
Version: 0.1.12
Summary: TripleO Terminal Dashboard
Home-page: https://github.com/d0ugal/python-tripleodash
Author: Dougal Matthews
Author-email: dougal@dougalmatthews.com
License: Apache-2
Keywords: tripleo
Platform: UNKNOWN
Classifier: Development Status :: 4 - Beta
Classifier: Environment :: Console
Classifier: Environment :: OpenStack
Classifier: Intended Audience :: Developers
Classifier: Intended Audience :: Information Technology
Classifier: License :: OSI Approved :: Apache Software License
Classifier: Operating System :: OS Independent
Classifier: Programming Language :: Python
Requires-Dist: urwid (==1.3.1)
Requires-Dist: python-heatclient (>=0.6.0)
Requires-Dist: python-ironicclient (>=1.1.0)
Requires-Dist: python-ironic-inspector-client (>=1.3.0)
Requires-Dist: cachetools (>=1.0.0)
